serverlessplus/__init__.py
serverlessplus/serverlessplus.py
serverlessplus-0.0.8.dist-info/LICENSE
serverlessplus-0.0.8.dist-info/METADATA
serverlessplus-0.0.8.dist-info/WHEEL
serverlessplus-0.0.8.dist-info/top_level.txt
serverlessplus-0.0.8.dist-info/RECORD
