Metadata-Version: 2.1
Name: serverlessplus
Version: 0.0.8
Summary: serverless your django/flask apps
Home-page: https://github.com/serverlessplus/py
Author: chenhengqi
Author-email: ritchiechen@tencent.com
License: Apache-2.0
Keywords: serverless,scf,tencent-cloud,wsgi,django,flask
Platform: UNKNOWN
Classifier: Development Status :: 3 - Alpha
Classifier: Intended Audience :: Developers
Classifier: Topic :: Software Development :: Build Tools
Classifier: License :: OSI Approved :: Apache Software License
Classifier: Programming Language :: Python :: 3
Classifier: Programming Language :: Python :: 3.4
Classifier: Programming Language :: Python :: 3.5
Classifier: Programming Language :: Python :: 3.6
Classifier: Programming Language :: Python :: 3.7
Requires-Dist: werkzeug
